<?xml version="1.0" encoding="utf-8"?>
<LanguageData>
  <!--The following translations were generated by https://www.deepl.com/-->
  <!-- EN: create glitterworld medicine -->
  <UACCreateGlitterworldMedicine.label>créer la médecine de glitterworld</UACCreateGlitterworldMedicine.label>
  <!-- EN: Create x5 glitterworld medicine from medicine and hyperweave. -->
  <UACCreateGlitterworldMedicine.description>Créer x5 glitterworld medicine à partir de medicine et d'hyperweave.</UACCreateGlitterworldMedicine.description>
  <!-- EN: create hyperweave -->
  <UACCreateHyperweave.label>créer un hyperweave</UACCreateHyperweave.label>
  <!-- EN: Create x75 hyperweave from cloth and components. -->
  <UACCreateHyperweave.description>Créer une hyper-tissure x75 à partir de tissu et de composants.</UACCreateHyperweave.description>
  <!-- EN: create medicine -->
  <UACCreateMedicine.label>créer des médicaments</UACCreateMedicine.label>
  <!-- EN: Creates x10 medicine from herbal medicine and synthread. -->
  <UACCreateMedicine.description>Crée x10 médicaments à partir de plantes médicinales et de fils synthétiques.</UACCreateMedicine.description>
  <!-- EN: create synthread -->
  <UACCreateSynthread.label>créer un fil de syndication</UACCreateSynthread.label>
  <!-- EN: Create x75 synthread from cloth, components and chemfuel. -->
  <UACCreateSynthread.description>Créer du fil synthétique x75 à partir de tissu, de composants et de carburant chimique.</UACCreateSynthread.description>
</LanguageData>
