<?xml version="1.0" encoding="utf-8"?>
<LanguageData>
  <!--The following translations were generated by https://www.deepl.com/-->
  <!-- EN: install UAC bionic eye -->
  <InstallUACbioniceye.label>installer l'œil bionique de l'UAC</InstallUACbioniceye.label>
  <!-- EN: Installs UAC bionic eye. -->
  <InstallUACbioniceye.description>Installe l'œil bionique de l'UAC.</InstallUACbioniceye.description>
  <!-- EN: Installing UAC bionic eye. -->
  <InstallUACbioniceye.jobString>Installation de l'œil bionique de l'UAC.</InstallUACbioniceye.jobString>
  <!-- EN: install UAC bionic spine -->
  <InstallUACbionicspine.label>installer UAC bionic spine</InstallUACbionicspine.label>
  <!-- EN: Installs UAC bionic spine. -->
  <InstallUACbionicspine.description>Installe la colonne vertébrale bionique de l'UAC.</InstallUACbionicspine.description>
  <!-- EN: Installing UAC bionic spine. -->
  <InstallUACbionicspine.jobString>Installation de la colonne vertébrale bionique de l'UAC.</InstallUACbionicspine.jobString>
  <!-- EN: install UAC brain chip -->
  <InstallUACBrainChip.label>installer une puce cérébrale UAC</InstallUACBrainChip.label>
  <!-- EN: Installs brain chip. -->
  <InstallUACBrainChip.description>Installe une puce cérébrale.</InstallUACBrainChip.description>
  <!-- EN: Installing UAC brain chip. -->
  <InstallUACBrainChip.jobString>Installation d'une puce cérébrale UAC.</InstallUACBrainChip.jobString>
  <!-- EN: install UAC learner implant -->
  <InstallUACLearnerImplant.label>installer l'implant d'apprentissage UAC</InstallUACLearnerImplant.label>
  <!-- EN: Installs UAC learner implant. -->
  <InstallUACLearnerImplant.description>Installe l'implant d'apprentissage UAC.</InstallUACLearnerImplant.description>
  <!-- EN: Installing UAC learner implant. -->
  <InstallUACLearnerImplant.jobString>Installation de l'implant d'apprentissage UAC.</InstallUACLearnerImplant.jobString>
  <!-- EN: install UAC synthetic Arm -->
  <InstallUACSyntheticArm.label>installer UAC synthétique Arm</InstallUACSyntheticArm.label>
  <!-- EN: Installs a UAC artificial arm. -->
  <InstallUACSyntheticArm.description>Installe un bras artificiel UAC.</InstallUACSyntheticArm.description>
  <!-- EN: Installing a UAC artificial arm. -->
  <InstallUACSyntheticArm.jobString>Installation d'un bras artificiel UAC.</InstallUACSyntheticArm.jobString>
  <!-- EN: install UAC synthetic ear -->
  <InstallUACSyntheticEar.label>installer l'oreille synthétique UAC</InstallUACSyntheticEar.label>
  <!-- EN: Installs a UAC artificial ear. -->
  <InstallUACSyntheticEar.description>Installe une oreille artificielle UAC.</InstallUACSyntheticEar.description>
  <!-- EN: Installing a UAC artificial ear. -->
  <InstallUACSyntheticEar.jobString>Installation d'une oreille artificielle UAC.</InstallUACSyntheticEar.jobString>
  <!-- EN: install UAC synthetic eye -->
  <InstallUACSyntheticEye.label>installer l'œil synthétique UAC</InstallUACSyntheticEye.label>
  <!-- EN: Installs a UAC artificial eye. -->
  <InstallUACSyntheticEye.description>Installe un œil artificiel UAC.</InstallUACSyntheticEye.description>
  <!-- EN: Installing a UAC artificial eye. -->
  <InstallUACSyntheticEye.jobString>Installation d'un œil artificiel UAC.</InstallUACSyntheticEye.jobString>
  <!-- EN: install UAC synthetic finger -->
  <InstallUACSyntheticFinger.label>installer le doigt synthétique UAC</InstallUACSyntheticFinger.label>
  <!-- EN: Installs a UAC artificial finger. -->
  <InstallUACSyntheticFinger.description>Installe un doigt artificiel UAC.</InstallUACSyntheticFinger.description>
  <!-- EN: Installing a UAC artificial finger. -->
  <InstallUACSyntheticFinger.jobString>Installation d'un doigt artificiel UAC.</InstallUACSyntheticFinger.jobString>
  <!-- EN: install UAC synthetic foot -->
  <InstallUACSyntheticFoot.label>installer le pied synthétique UAC</InstallUACSyntheticFoot.label>
  <!-- EN: Installs a UAC artificial foot. -->
  <InstallUACSyntheticFoot.description>Installe un pied artificiel UAC.</InstallUACSyntheticFoot.description>
  <!-- EN: Installing a UAC artificial foot. -->
  <InstallUACSyntheticFoot.jobString>Installation d'un pied artificiel UAC.</InstallUACSyntheticFoot.jobString>
  <!-- EN: install UAC synthetic hand -->
  <InstallUACSyntheticHand.label>installer l'UAC à la main synthétique</InstallUACSyntheticHand.label>
  <!-- EN: Installs a UAC artificial hand. -->
  <InstallUACSyntheticHand.description>Installe une main artificielle UAC.</InstallUACSyntheticHand.description>
  <!-- EN: Installing a UAC artificial hand. -->
  <InstallUACSyntheticHand.jobString>Installation d'une main artificielle UAC.</InstallUACSyntheticHand.jobString>
  <!-- EN: install UAC synthetic heart -->
  <InstallUACSyntheticHeart.label>installer UAC cœur synthétique</InstallUACSyntheticHeart.label>
  <!-- EN: Installs a UAC artificial heart. -->
  <InstallUACSyntheticHeart.description>Installe un coeur artificiel UAC.</InstallUACSyntheticHeart.description>
  <!-- EN: Installing a UAC artificial heart. -->
  <InstallUACSyntheticHeart.jobString>Installation d'un coeur artificiel UAC.</InstallUACSyntheticHeart.jobString>
  <!-- EN: install UAC synthetic jaw -->
  <InstallUACSyntheticJaw.label>installer la mâchoire synthétique de l'UAC</InstallUACSyntheticJaw.label>
  <!-- EN: Installs a UAC artificial jaw. -->
  <InstallUACSyntheticJaw.description>Installe une mâchoire artificielle UAC.</InstallUACSyntheticJaw.description>
  <!-- EN: Installing a UAC artificial jaw. -->
  <InstallUACSyntheticJaw.jobString>Installation d'une mâchoire artificielle UAC.</InstallUACSyntheticJaw.jobString>
  <!-- EN: install UAC synthetic kidney -->
  <InstallUACSyntheticKidney.label>installer le rein synthétique UAC</InstallUACSyntheticKidney.label>
  <!-- EN: Installs UAC synthetic kidney. -->
  <InstallUACSyntheticKidney.description>Installe le rein synthétique UAC.</InstallUACSyntheticKidney.description>
  <!-- EN: Installing UAC synthetic kidney. -->
  <InstallUACSyntheticKidney.jobString>Installation d'un rein synthétique UAC.</InstallUACSyntheticKidney.jobString>
  <!-- EN: install UAC synthetic leg -->
  <InstallUACSyntheticLeg.label>installer la jambe synthétique UAC</InstallUACSyntheticLeg.label>
  <!-- EN: Installs a UAC artificial leg. -->
  <InstallUACSyntheticLeg.description>Installe une jambe artificielle UAC.</InstallUACSyntheticLeg.description>
  <!-- EN: Installing a UAC artificial leg. -->
  <InstallUACSyntheticLeg.jobString>Installation d'une jambe artificielle UAC.</InstallUACSyntheticLeg.jobString>
  <!-- EN: install UAC synthetic liver -->
  <InstallUACSyntheticLiver.label>installer le foie synthétique UAC</InstallUACSyntheticLiver.label>
  <!-- EN: Installs a UAC synthetic liver. -->
  <InstallUACSyntheticLiver.description>Installe un foie synthétique UAC.</InstallUACSyntheticLiver.description>
  <!-- EN: Installing UAC synthetic liver. -->
  <InstallUACSyntheticLiver.jobString>Installation du foie synthétique UAC.</InstallUACSyntheticLiver.jobString>
  <!-- EN: install UAC synthetic lung -->
  <InstallUACSyntheticLung.label>installer le poumon synthétique UAC</InstallUACSyntheticLung.label>
  <!-- EN: Installs UAC synthetic lung. -->
  <InstallUACSyntheticLung.description>Installe le poumon synthétique UAC.</InstallUACSyntheticLung.description>
  <!-- EN: Installing UAC synthetic lung. -->
  <InstallUACSyntheticLung.jobString>Installation du poumon synthétique UAC.</InstallUACSyntheticLung.jobString>
  <!-- EN: install UAC synthetic nose -->
  <InstallUACSyntheticNose.label>installer UAC synthetic nose</InstallUACSyntheticNose.label>
  <!-- EN: Installs a UAC artificial nose. -->
  <InstallUACSyntheticNose.description>Installe un nez artificiel UAC.</InstallUACSyntheticNose.description>
  <!-- EN: Installing a UAC artificial nose. -->
  <InstallUACSyntheticNose.jobString>Installation d'un nez artificiel UAC.</InstallUACSyntheticNose.jobString>
  <!-- EN: install UAC synthetic stomach -->
  <InstallUACSyntheticStomach.label>installer l'estomac synthétique UAC</InstallUACSyntheticStomach.label>
  <!-- EN: Installs UAC synthetic stomach. -->
  <InstallUACSyntheticStomach.description>Installe l'estomac synthétique UAC.</InstallUACSyntheticStomach.description>
  <!-- EN: Installing UAC synthetic stomach. -->
  <InstallUACSyntheticStomach.jobString>Installation de l'estomac synthétique UAC.</InstallUACSyntheticStomach.jobString>
  <!-- EN: install UAC synthetic toe -->
  <InstallUACSyntheticToe.label>installer UAC synthetic toe</InstallUACSyntheticToe.label>
  <!-- EN: Installs a UAC artificial toe. -->
  <InstallUACSyntheticToe.description>Installe un orteil artificiel UAC.</InstallUACSyntheticToe.description>
  <!-- EN: Installing a UAC artificial toe. -->
  <InstallUACSyntheticToe.jobString>Installation d'un orteil artificiel UAC.</InstallUACSyntheticToe.jobString>
  <!-- EN: install UAC worker implant -->
  <InstallUACWorkerImplant.label>installer l'implant de travailleur UAC</InstallUACWorkerImplant.label>
  <!-- EN: Installs UAC worker implant. -->
  <InstallUACWorkerImplant.description>Installe l'implant UAC.</InstallUACWorkerImplant.description>
  <!-- EN: Installing UAC worker implant. -->
  <InstallUACWorkerImplant.jobString>Installation de l'implant UAC.</InstallUACWorkerImplant.jobString>
  <!-- EN: install UAC combat implant -->
  <UACCombatImplant.label>installer l'implant de combat UAC</UACCombatImplant.label>
  <!-- EN: Installs UAC combat implant. -->
  <UACCombatImplant.description>Installe l'implant de combat UAC.</UACCombatImplant.description>
  <!-- EN: Installing UAC combat implant. -->
  <UACCombatImplant.jobString>Installation de l'implant de combat UAC.</UACCombatImplant.jobString>
</LanguageData>
